allgraph/__init__.py
allgraph/main.py
allgraph-0.1.dist-info/METADATA
allgraph-0.1.dist-info/WHEEL
allgraph-0.1.dist-info/top_level.txt
allgraph-0.1.dist-info/RECORD
