Metadata-Version: 2.1
Name: allgraph
Version: 0.1
Summary: A library for creating various types of graphs
Home-page: https://github.com/yourusername/allgraph
Author: Your Name
Author-email: your.email@example.com
Classifier: Programming Language :: Python :: 3
Classifier: License :: OSI Approved :: MIT License
Classifier: Operating System :: OS Independent
Requires-Python: >=3.6
Requires-Dist: matplotlib
